[
	{
		"name" : "Named HTML Entities",
		"glyphs" : [
			{ "name": "nbsp", "html": "&nbsp;", "desc": "no-break space (non-breaking space)" },
			{ "name": "quot", "html": "&quot;", "desc": "quotation mark (APL quote)" },
			{ "name": "apos", "html": "&apos;", "desc": "apostrophe (apostrophe-quote)" },
			{ "name": "amp", "html": "&amp;", "desc": "ampersand" },
			{ "name": "lt", "html": "&lt;", "desc": "less-than sign" },
			{ "name": "gt", "html": "&gt;", "desc": "greater-than sign" },
			{ "name": "iexcl", "html": "&iexcl;", "desc": "inverted exclamation mark" },
			{ "name": "cent", "html": "&cent;", "desc": "cent sign" },
			{ "name": "pound", "html": "&pound;", "desc": "pound sign" },
			{ "name": "curren", "html": "&curren;", "desc": "currency sign" },
			{ "name": "yen", "html": "&yen;", "desc": "yen sign (yuan sign)" },
			{ "name": "brvbar", "html": "&brvbar;", "desc": "broken bar (broken vertical bar)" },
			{ "name": "sect", "html": "&sect;", "desc": "section sign" },
			{ "name": "uml", "html": "&uml;", "desc": "diaeresis (spacing diaeresis)" },
			{ "name": "copy", "html": "&copy;", "desc": "copyright symbol" },
			{ "name": "reg", "html": "&reg;", "desc": "registered sign (registered trademark symbol)" },
			{ "name": "trade", "html": "&trade;", "desc": "trademark symbol" },
			{ "name": "ordf", "html": "&ordf;", "desc": "feminine ordinal indicator" },
			{ "name": "laquo", "html": "&laquo;", "desc": "left-pointing double angle quotation mark (left pointing guillemet)" },
			{ "name": "raquo", "html": "&raquo;", "desc": "right-pointing double angle quotation mark (right pointing guillemet)" },
			{ "name": "not", "html": "&not;", "desc": "not sign" },
			{ "name": "macr", "html": "&macr;", "desc": "macron (spacing macron, overline, APL overbar)" },
			{ "name": "deg", "html": "&deg;", "desc": "degree symbol" },
			{ "name": "plusmn", "html": "&plusmn;", "desc": "plus-minus sign (plus-or-minus sign)" },
			{ "name": "sup1", "html": "&sup1;", "desc": "superscript one (superscript digit one)" },
			{ "name": "sup2", "html": "&sup2;", "desc": "superscript two (superscript digit two, squared)" },
			{ "name": "sup3", "html": "&sup3;", "desc": "superscript three (superscript digit three, cubed)" },
			{ "name": "acute", "html": "&acute;", "desc": "acute accent (spacing acute)" },
			{ "name": "micro", "html": "&micro;", "desc": "micro sign" },
			{ "name": "para", "html": "&para;", "desc": "pilcrow sign (paragraph sign)" },
			{ "name": "middot", "html": "&middot;", "desc": "middle dot (Georgian comma, Greek middle dot)" },
			{ "name": "cedil", "html": "&cedil;", "desc": "cedilla (spacing cedilla)" },
			{ "name": "ordm", "html": "&ordm;", "desc": "masculine ordinal indicator" },
			{ "name": "frac14", "html": "&frac14;", "desc": "vulgar fraction one quarter (fraction one quarter)" },
			{ "name": "frac12", "html": "&frac12;", "desc": "vulgar fraction one half (fraction one half)" },
			{ "name": "frac34", "html": "&frac34;", "desc": "vulgar fraction three quarters (fraction three quarters)" },
			{ "name": "iquest", "html": "&iquest;", "desc": "inverted question mark (turned question mark)" },
			{ "name": "Agrave", "html": "&Agrave;", "desc": "Latin capital letter A with grave accent (Latin capital letter A grave)" },
			{ "name": "Aacute", "html": "&Aacute;", "desc": "Latin capital letter A with acute accent" },
			{ "name": "Acirc", "html": "&Acirc;", "desc": "Latin capital letter A with circumflex" },
			{ "name": "Atilde", "html": "&Atilde;", "desc": "Latin capital letter A with tilde" },
			{ "name": "Auml", "html": "&Auml;", "desc": "Latin capital letter A with diaeresis" },
			{ "name": "Aring", "html": "&Aring;", "desc": "Latin capital letter A with ring above (Latin capital letter A ring)" },
			{ "name": "AElig", "html": "&AElig;", "desc": "Latin capital letter AE (Latin capital ligature AE)" },
			{ "name": "Ccedil", "html": "&Ccedil;", "desc": "Latin capital letter C with cedilla" },
			{ "name": "Egrave", "html": "&Egrave;", "desc": "Latin capital letter E with grave accent" },
			{ "name": "Eacute", "html": "&Eacute;", "desc": "Latin capital letter E with acute accent" },
			{ "name": "Ecirc", "html": "&Ecirc;", "desc": "Latin capital letter E with circumflex" },
			{ "name": "Euml", "html": "&Euml;", "desc": "Latin capital letter E with diaeresis" },
			{ "name": "Igrave", "html": "&Igrave;", "desc": "Latin capital letter I with grave accent" },
			{ "name": "Iacute", "html": "&Iacute;", "desc": "Latin capital letter I with acute accent" },
			{ "name": "Icirc", "html": "&Icirc;", "desc": "Latin capital letter I with circumflex" },
			{ "name": "Iuml", "html": "&Iuml;", "desc": "Latin capital letter I with diaeresis" },
			{ "name": "ETH", "html": "&ETH;", "desc": "Latin capital letter Eth" },
			{ "name": "Ntilde", "html": "&Ntilde;", "desc": "Latin capital letter N with tilde" },
			{ "name": "Ograve", "html": "&Ograve;", "desc": "Latin capital letter O with grave accent" },
			{ "name": "Oacute", "html": "&Oacute;", "desc": "Latin capital letter O with acute accent" },
			{ "name": "Ocirc", "html": "&Ocirc;", "desc": "Latin capital letter O with circumflex" },
			{ "name": "Otilde", "html": "&Otilde;", "desc": "Latin capital letter O with tilde" },
			{ "name": "Ouml", "html": "&Ouml;", "desc": "Latin capital letter O with diaeresis" },
			{ "name": "times", "html": "&times;", "desc": "multiplication sign" },
			{ "name": "Oslash", "html": "&Oslash;", "desc": "Latin capital letter O with stroke (Latin capital letter O slash)" },
			{ "name": "Ugrave", "html": "&Ugrave;", "desc": "Latin capital letter U with grave accent" },
			{ "name": "Uacute", "html": "&Uacute;", "desc": "Latin capital letter U with acute accent" },
			{ "name": "Ucirc", "html": "&Ucirc;", "desc": "Latin capital letter U with circumflex" },
			{ "name": "Uuml", "html": "&Uuml;", "desc": "Latin capital letter U with diaeresis" },
			{ "name": "Yacute", "html": "&Yacute;", "desc": "Latin capital letter Y with acute accent" },
			{ "name": "THORN", "html": "&THORN;", "desc": "Latin capital letter THORN" },
			{ "name": "szlig", "html": "&szlig;", "desc": "Latin small letter sharp s (ess-zed)" },
			{ "name": "agrave", "html": "&agrave;", "desc": "Latin small letter a with grave accent" },
			{ "name": "aacute", "html": "&aacute;", "desc": "Latin small letter a with acute accent" },
			{ "name": "acirc", "html": "&acirc;", "desc": "Latin small letter a with circumflex" },
			{ "name": "atilde", "html": "&atilde;", "desc": "Latin small letter a with tilde" },
			{ "name": "auml", "html": "&auml;", "desc": "Latin small letter a with diaeresis" },
			{ "name": "aring", "html": "&aring;", "desc": "Latin small letter a with ring above" },
			{ "name": "aelig", "html": "&aelig;", "desc": "Latin small letter ae (Latin small ligature ae)" },
			{ "name": "ccedil", "html": "&ccedil;", "desc": "Latin small letter c with cedilla" },
			{ "name": "egrave", "html": "&egrave;", "desc": "Latin small letter e with grave accent" },
			{ "name": "eacute", "html": "&eacute;", "desc": "Latin small letter e with acute accent" },
			{ "name": "ecirc", "html": "&ecirc;", "desc": "Latin small letter e with circumflex" },
			{ "name": "euml", "html": "&euml;", "desc": "Latin small letter e with diaeresis" },
			{ "name": "igrave", "html": "&igrave;", "desc": "Latin small letter i with grave accent" },
			{ "name": "iacute", "html": "&iacute;", "desc": "Latin small letter i with acute accent" },
			{ "name": "icirc", "html": "&icirc;", "desc": "Latin small letter i with circumflex" },
			{ "name": "iuml", "html": "&iuml;", "desc": "Latin small letter i with diaeresis" },
			{ "name": "eth", "html": "&eth;", "desc": "Latin small letter eth" },
			{ "name": "ntilde", "html": "&ntilde;", "desc": "Latin small letter n with tilde" },
			{ "name": "ograve", "html": "&ograve;", "desc": "Latin small letter o with grave accent" },
			{ "name": "oacute", "html": "&oacute;", "desc": "Latin small letter o with acute accent" },
			{ "name": "ocirc", "html": "&ocirc;", "desc": "Latin small letter o with circumflex" },
			{ "name": "otilde", "html": "&otilde;", "desc": "Latin small letter o with tilde" },
			{ "name": "ouml", "html": "&ouml;", "desc": "Latin small letter o with diaeresis" },
			{ "name": "divide", "html": "&divide;", "desc": "division sign (obelus)" },
			{ "name": "oslash", "html": "&oslash;", "desc": "Latin small letter o with stroke (Latin small letter o slash)" },
			{ "name": "ugrave", "html": "&ugrave;", "desc": "Latin small letter u with grave accent" },
			{ "name": "uacute", "html": "&uacute;", "desc": "Latin small letter u with acute accent" },
			{ "name": "ucirc", "html": "&ucirc;", "desc": "Latin small letter u with circumflex" },
			{ "name": "uuml", "html": "&uuml;", "desc": "Latin small letter u with diaeresis" },
			{ "name": "yacute", "html": "&yacute;", "desc": "Latin small letter y with acute accent" },
			{ "name": "thorn", "html": "&thorn;", "desc": "Latin small letter thorn" },
			{ "name": "yuml", "html": "&yuml;", "desc": "Latin small letter y with diaeresis" },
			{ "name": "OElig", "html": "&OElig;", "desc": "Latin capital ligature oe" },
			{ "name": "oelig", "html": "&oelig;", "desc": "Latin small ligature oe" },
			{ "name": "Scaron", "html": "&Scaron;", "desc": "Latin capital letter s with caron" },
			{ "name": "scaron", "html": "&scaron;", "desc": "Latin small letter s with caron" },
			{ "name": "Yuml", "html": "&Yuml;", "desc": "Latin capital letter y with diaeresis" },
			{ "name": "fnof", "html": "&fnof;", "desc": "Latin small letter f with hook (function, florin)" },
			{ "name": "circ", "html": "&circ;", "desc": "modifier letter circumflex accent" },
			{ "name": "tilde", "html": "&tilde;", "desc": "small tilde" },
			{ "name": "Alpha", "html": "&Alpha;", "desc": "Greek capital letter Alpha" },
			{ "name": "Beta", "html": "&Beta;", "desc": "Greek capital letter Beta" },
			{ "name": "Gamma", "html": "&Gamma;", "desc": "Greek capital letter Gamma" },
			{ "name": "Delta", "html": "&Delta;", "desc": "Greek capital letter Delta" },
			{ "name": "Epsilon", "html": "&Epsilon;", "desc": "Greek capital letter Epsilon" },
			{ "name": "Zeta", "html": "&Zeta;", "desc": "Greek capital letter Zeta" },
			{ "name": "Eta", "html": "&Eta;", "desc": "Greek capital letter Eta" },
			{ "name": "Theta", "html": "&Theta;", "desc": "Greek capital letter Theta" },
			{ "name": "Iota", "html": "&Iota;", "desc": "Greek capital letter Iota" },
			{ "name": "Kappa", "html": "&Kappa;", "desc": "Greek capital letter Kappa" },
			{ "name": "Lambda", "html": "&Lambda;", "desc": "Greek capital letter Lambda" },
			{ "name": "Mu", "html": "&Mu;", "desc": "Greek capital letter Mu" },
			{ "name": "Nu", "html": "&Nu;", "desc": "Greek capital letter Nu" },
			{ "name": "Xi", "html": "&Xi;", "desc": "Greek capital letter Xi" },
			{ "name": "Omicron", "html": "&Omicron;", "desc": "Greek capital letter Omicron" },
			{ "name": "Pi", "html": "&Pi;", "desc": "Greek capital letter Pi" },
			{ "name": "Rho", "html": "&Rho;", "desc": "Greek capital letter Rho" },
			{ "name": "Sigma", "html": "&Sigma;", "desc": "Greek capital letter Sigma" },
			{ "name": "Tau", "html": "&Tau;", "desc": "Greek capital letter Tau" },
			{ "name": "Upsilon", "html": "&Upsilon;", "desc": "Greek capital letter Upsilon" },
			{ "name": "Phi", "html": "&Phi;", "desc": "Greek capital letter Phi" },
			{ "name": "Chi", "html": "&Chi;", "desc": "Greek capital letter Chi" },
			{ "name": "Psi", "html": "&Psi;", "desc": "Greek capital letter Psi" },
			{ "name": "Omega", "html": "&Omega;", "desc": "Greek capital letter Omega" },
			{ "name": "alpha", "html": "&alpha;", "desc": "Greek small letter alpha" },
			{ "name": "beta", "html": "&beta;", "desc": "Greek small letter beta" },
			{ "name": "gamma", "html": "&gamma;", "desc": "Greek small letter gamma" },
			{ "name": "delta", "html": "&delta;", "desc": "Greek small letter delta" },
			{ "name": "epsilon", "html": "&epsilon;", "desc": "Greek small letter epsilon" },
			{ "name": "zeta", "html": "&zeta;", "desc": "Greek small letter zeta" },
			{ "name": "eta", "html": "&eta;", "desc": "Greek small letter eta" },
			{ "name": "theta", "html": "&theta;", "desc": "Greek small letter theta" },
			{ "name": "iota", "html": "&iota;", "desc": "Greek small letter iota" },
			{ "name": "kappa", "html": "&kappa;", "desc": "Greek small letter kappa" },
			{ "name": "lambda", "html": "&lambda;", "desc": "Greek small letter lambda" },
			{ "name": "mu", "html": "&mu;", "desc": "Greek small letter mu" },
			{ "name": "nu", "html": "&nu;", "desc": "Greek small letter nu" },
			{ "name": "xi", "html": "&xi;", "desc": "Greek small letter xi" },
			{ "name": "omicron", "html": "&omicron;", "desc": "Greek small letter omicron" },
			{ "name": "pi", "html": "&pi;", "desc": "Greek small letter pi" },
			{ "name": "rho", "html": "&rho;", "desc": "Greek small letter rho" },
			{ "name": "sigmaf", "html": "&sigmaf;", "desc": "Greek small letter final sigma" },
			{ "name": "sigma", "html": "&sigma;", "desc": "Greek small letter sigma" },
			{ "name": "tau", "html": "&tau;", "desc": "Greek small letter tau" },
			{ "name": "upsilon", "html": "&upsilon;", "desc": "Greek small letter upsilon" },
			{ "name": "phi", "html": "&phi;", "desc": "Greek small letter phi" },
			{ "name": "chi", "html": "&chi;", "desc": "Greek small letter chi" },
			{ "name": "psi", "html": "&psi;", "desc": "Greek small letter psi" },
			{ "name": "omega", "html": "&omega;", "desc": "Greek small letter omega" },
			{ "name": "thetasym", "html": "&thetasym;", "desc": "Greek theta symbol" },
			{ "name": "upsih", "html": "&upsih;", "desc": "Greek Upsilon with hook symbol" },
			{ "name": "piv", "html": "&piv;", "desc": "Greek pi symbol" },
			{ "name": "ndash", "html": "&ndash;", "desc": "en dash" },
			{ "name": "mdash", "html": "&mdash;", "desc": "em dash" },
			{ "name": "lsquo", "html": "&lsquo;", "desc": "left single quotation mark" },
			{ "name": "rsquo", "html": "&rsquo;", "desc": "right single quotation mark" },
			{ "name": "sbquo", "html": "&sbquo;", "desc": "single low-9 quotation mark" },
			{ "name": "ldquo", "html": "&ldquo;", "desc": "left double quotation mark" },
			{ "name": "rdquo", "html": "&rdquo;", "desc": "right double quotation mark" },
			{ "name": "bdquo", "html": "&bdquo;", "desc": "double low-9 quotation mark" },
			{ "name": "dagger", "html": "&dagger;", "desc": "dagger, obelisk" },
			{ "name": "Dagger", "html": "&Dagger;", "desc": "double dagger, double obelisk" },
			{ "name": "bull", "html": "&bull;", "desc": "bullet (black small circle)" },
			{ "name": "hellip", "html": "&hellip;", "desc": "horizontal ellipsis (three dot leader)" },
			{ "name": "permil", "html": "&permil;", "desc": "per mille sign" },
			{ "name": "prime", "html": "&prime;", "desc": "prime (minutes, feet)" },
			{ "name": "Prime", "html": "&Prime;", "desc": "double prime (seconds, inches)" },
			{ "name": "lsaquo", "html": "&lsaquo;", "desc": "single left-pointing angle quotation mark" },
			{ "name": "rsaquo", "html": "&rsaquo;", "desc": "single right-pointing angle quotation mark" },
			{ "name": "oline", "html": "&oline;", "desc": "overline (spacing overscore)" },
			{ "name": "frasl", "html": "&frasl;", "desc": "fraction slash (solidus)" },
			{ "name": "euro", "html": "&euro;", "desc": "euro sign" },
			{ "name": "image", "html": "&image;", "desc": "black-letter capital I (imaginary part)" },
			{ "name": "weierp", "html": "&weierp;", "desc": "script capital P (power set, Weierstrass p)" },
			{ "name": "real", "html": "&real;", "desc": "black-letter capital R (real part symbol)" },
			{ "name": "alefsym", "html": "&alefsym;", "desc": "alef symbol (first transfinite cardinal)" },
			{ "name": "larr", "html": "&larr;", "desc": "leftwards arrow" },
			{ "name": "uarr", "html": "&uarr;", "desc": "upwards arrow" },
			{ "name": "rarr", "html": "&rarr;", "desc": "rightwards arrow" },
			{ "name": "darr", "html": "&darr;", "desc": "downwards arrow" },
			{ "name": "harr", "html": "&harr;", "desc": "left right arrow" },
			{ "name": "crarr", "html": "&crarr;", "desc": "downwards arrow with corner leftwards (carriage return)" },
			{ "name": "lArr", "html": "&lArr;", "desc": "leftwards double arrow" },
			{ "name": "uArr", "html": "&uArr;", "desc": "upwards double arrow" },
			{ "name": "rArr", "html": "&rArr;", "desc": "rightwards double arrow" },
			{ "name": "dArr", "html": "&dArr;", "desc": "downwards double arrow" },
			{ "name": "hArr", "html": "&hArr;", "desc": "left right double arrow" },
			{ "name": "forall", "html": "&forall;", "desc": "for all" },
			{ "name": "part", "html": "&part;", "desc": "partial differential" },
			{ "name": "exist", "html": "&exist;", "desc": "there exists" },
			{ "name": "empty", "html": "&empty;", "desc": "empty set (null set)" },
			{ "name": "nabla", "html": "&nabla;", "desc": "del or nabla (vector differential operator)" },
			{ "name": "isin", "html": "&isin;", "desc": "element of" },
			{ "name": "notin", "html": "&notin;", "desc": "not an element of" },
			{ "name": "ni", "html": "&ni;", "desc": "contains as member" },
			{ "name": "prod", "html": "&prod;", "desc": "n-ary product (product sign)" },
			{ "name": "sum", "html": "&sum;", "desc": "n-ary summation" },
			{ "name": "minus", "html": "&minus;", "desc": "minus sign" },
			{ "name": "lowast", "html": "&lowast;", "desc": "asterisk operator" },
			{ "name": "radic", "html": "&radic;", "desc": "square root (radical sign)" },
			{ "name": "prop", "html": "&prop;", "desc": "proportional to" },
			{ "name": "infin", "html": "&infin;", "desc": "infinity" },
			{ "name": "ang", "html": "&ang;", "desc": "angle" },
			{ "name": "and", "html": "&and;", "desc": "logical and (wedge)" },
			{ "name": "or", "html": "&or;", "desc": "logical or (vee)" },
			{ "name": "cap", "html": "&cap;", "desc": "intersection (cap)" },
			{ "name": "cup", "html": "&cup;", "desc": "union (cup)" },
			{ "name": "int", "html": "&int;", "desc": "integral" },
			{ "name": "there4", "html": "&there4;", "desc": "therefore sign" },
			{ "name": "sim", "html": "&sim;", "desc": "tilde operator (varies with, similar to)" },
			{ "name": "cong", "html": "&cong;", "desc": "congruent to" },
			{ "name": "asymp", "html": "&asymp;", "desc": "almost equal to (asymptotic to)" },
			{ "name": "ne", "html": "&ne;", "desc": "not equal to" },
			{ "name": "equiv", "html": "&equiv;", "desc": "identical to; equivalent to" },
			{ "name": "le", "html": "&le;", "desc": "less-than or equal to" },
			{ "name": "ge", "html": "&ge;", "desc": "greater-than or equal to" },
			{ "name": "sub", "html": "&sub;", "desc": "subset of" },
			{ "name": "sup", "html": "&sup;", "desc": "superset of" },
			{ "name": "nsub", "html": "&nsub;", "desc": "not a subset of" },
			{ "name": "sube", "html": "&sube;", "desc": "subset of or equal to" },
			{ "name": "supe", "html": "&supe;", "desc": "superset of or equal to" },
			{ "name": "oplus", "html": "&oplus;", "desc": "circled plus (direct sum)" },
			{ "name": "otimes", "html": "&otimes;", "desc": "circled times (vector product)" },
			{ "name": "perp", "html": "&perp;", "desc": "up tack (orthogonal to, perpendicular)" },
			{ "name": "sdot", "html": "&sdot;", "desc": "dot operator" },
			{ "name": "lceil", "html": "&lceil;", "desc": "left ceiling (APL upstile)" },
			{ "name": "rceil", "html": "&rceil;", "desc": "right ceiling" },
			{ "name": "lfloor", "html": "&lfloor;", "desc": "left floor (APL downstile)" },
			{ "name": "rfloor", "html": "&rfloor;", "desc": "right floor" },
			{ "name": "lang", "html": "&lang;", "desc": "left-pointing angle bracket (bra)" },
			{ "name": "rang", "html": "&rang;", "desc": "right-pointing angle bracket (ket)" },
			{ "name": "loz", "html": "&loz;", "desc": "lozenge" },
			{ "name": "spades", "html": "&spades;", "desc": "black spade suit" },
			{ "name": "clubs", "html": "&clubs;", "desc": "black club suit (shamrock)" },
			{ "name": "hearts", "html": "&hearts;", "desc": "black heart suit (valentine)" },
			{ "name": "diams", "html": "&diams;", "desc": "black diamond suit" }
		]
	}
]